setup.cfg
setup.py
pogocpm2level/__init__.py
pogocpm2level/cpm2level.py
pogocpm2level.egg-info/PKG-INFO
pogocpm2level.egg-info/SOURCES.txt
pogocpm2level.egg-info/dependency_links.txt
pogocpm2level.egg-info/top_level.txt