Metadata-Version: 1.1
Name: pogocpm2level
Version: 1.0.0
Summary: Easily calculate the level of a given Pokémon in Pokémon GO based on its total CP multiplier value.
Home-page: https://github.com/mathiasbynens/pogocpm2level
Author: Mathias Bynens
Author-email: mathias@qiwi.be
License: MIT
Download-URL: https://github.com/mathiasbynens/pogocpm2level/tarball/v1.0.1
Keywords: pogo,pokemon go,cpm
Platform: UNKNOWN
